LICENSE.txt
README.md
setup.py
turbocase/__init__.py
turbocase/__main__.py
turbocase/cases.py
turbocase/kicad.py
turbocase/scad.py
turbocase/svg.py
turbocase/vector.py
turbocase.egg-info/PKG-INFO
turbocase.egg-info/SOURCES.txt
turbocase.egg-info/dependency_links.txt
turbocase.egg-info/entry_points.txt
turbocase.egg-info/requires.txt
turbocase.egg-info/top_level.txt
turbocase/parts/__init__.py
turbocase/parts/batteryholder.py
turbocase/parts/case.py
turbocase/parts/cutout.py
turbocase/parts/keyhole.py
turbocase/parts/screws.py
turbocase/parts/shape.py